CONTRIBUTING.md
Jenkinsfile
MANIFEST.in
README.rst
setup.cfg
setup.py
buildouts/plone4/buildout.cfg
buildouts/plone4/install.sh
buildouts/plone4/versions.cfg
docs/HISTORY.txt
docs/INSTALL.txt
docs/LICENSE.GPL
docs/LICENSE.txt
eea/__init__.py
eea.icons.egg-info/PKG-INFO
eea.icons.egg-info/SOURCES.txt
eea.icons.egg-info/dependency_links.txt
eea.icons.egg-info/entry_points.txt
eea.icons.egg-info/namespace_packages.txt
eea.icons.egg-info/not-zip-safe
eea.icons.egg-info/requires.txt
eea.icons.egg-info/top_level.txt
eea/icons/README.txt
eea/icons/__init__.py
eea/icons/config.py
eea/icons/configure.zcml
eea/icons/interfaces.py
eea/icons/profiles.zcml
eea/icons/skins.zcml
eea/icons/version.txt
eea/icons/Extensions/install.py
eea/icons/profiles/default/browserlayer.xml
eea/icons/profiles/default/cssregistry.xml
eea/icons/profiles/default/eea.icons.txt
eea/icons/profiles/default/jsregistry.xml
eea/icons/profiles/default/metadata.xml
eea/icons/profiles/default/skins.xml
eea/icons/profiles/uninstall/browserlayer.xml
eea/icons/profiles/uninstall/cssregistry.xml
eea/icons/profiles/uninstall/eea.icons.uninstall.txt
eea/icons/profiles/uninstall/jsregistry.xml
eea/icons/profiles/uninstall/skins.xml
eea/icons/skins/eea_icons_fonts/FontAwesome.otf.dtml
eea/icons/skins/eea_icons_fonts/fontawesome-webfont.eot.dtml
eea/icons/skins/eea_icons_fonts/fontawesome-webfont.svg.dtml
eea/icons/skins/eea_icons_fonts/fontawesome-webfont.ttf.dtml
eea/icons/skins/eea_icons_fonts/fontawesome-webfont.woff.dtml
eea/icons/skins/eea_icons_fonts/fontawesome-webfont.woff2.dtml
eea/icons/skins/eea_icons_javascripts/eea-icons.js
eea/icons/skins/eea_icons_styles/eea-icons-animation.css.dtml
eea/icons/skins/eea_icons_styles/eea-icons.css.dtml
eea/icons/tests/__init__.py
eea/icons/tests/base.py
eea/icons/tests/test_doctest.py
eea/icons/upgrades/__init__.py
eea/icons/upgrades/configure.zcml